sorting_nz_style/__init__.py
sorting_nz_style/bubble_sort.py
sorting_nz_style/insertion_sort.py
sorting_nz_style/quick_sort.py
sorting_nz_style/selection_sort.py
sorting_nz_style/sort_tests.py
sorting_nz_style/sorters_test.py
sortit/__init__.py
sortit/bubble_sort.py
sortit/insertion_sort.py
sortit/quick_sort.py
sortit/selection_sort.py
sortit/sort_tests.py
sortit/sorters_test.py
sortit-0.3.dist-info/METADATA
sortit-0.3.dist-info/WHEEL
sortit-0.3.dist-info/top_level.txt
sortit-0.3.dist-info/RECORD
