Metadata-Version: 2.1
Name: sortit
Version: 0.3
Summary: some sorting functions
Home-page: http://github.com/storborg/funniest
Author: Sortmaster X
Author-email: sortmasterx@sortit.com
License: MIT
Platform: UNKNOWN
